[
  {
    "key": "OH",
    "value": 46100
  },
  {
    "key": "WV",
    "value": 1951
  },
  {
    "key": "CA",
    "value": 484706
  },
  {
    "key": "FL",
    "value": 177490
  },
  {
    "key": "GA",
    "value": 66637
  },
  {
    "key": "SC",
    "value": 99890
  },
  {
    "key": "NE",
    "value": 19328
  },
  {
    "key": "IA",
    "value": 8336
  },
  {
    "key": "IL",
    "value": 71701
  },
  {
    "key": "MO",
    "value": 22481
  },
  {
    "key": "WI",
    "value": 12884
  },
  {
    "key": "IN",
    "value": 24162
  },
  {
    "key": "MI",
    "value": 74045
  },
  {
    "key": "NJ",
    "value": 40346
  },
  {
    "key": "NY",
    "value": 105523
  },
  {
    "key": "CT",
    "value": 18708
  },
  {
    "key": "MA",
    "value": 26096
  },
  {
    "key": "RI",
    "value": 8298
  },
  {
    "key": "NH",
    "value": 5593
  },
  {
    "key": "PA",
    "value": 75814
  },
  {
    "key": "KY",
    "value": 13765
  },
  {
    "key": "MD",
    "value": 34315
  },
  {
    "key": "VA",
    "value": 61426
  },
  {
    "key": "DC",
    "value": 2558
  },
  {
    "key": "DE",
    "value": 3124
  },
  {
    "key": "TX",
    "value": 237637
  },
  {
    "key": "WA",
    "value": 50480
  },
  {
    "key": "OR",
    "value": 42565
  },
  {
    "key": "AL",
    "value": 22063
  },
  {
    "key": "TN",
    "value": 42464
  },
  {
    "key": "NC",
    "value": 108916
  },
  {
    "key": "MN",
    "value": 40000
  },
  {
    "key": "KS",
    "value": 5486
  },
  {
    "key": "OK",
    "value": 36183
  },
  {
    "key": "LA",
    "value": 38143
  },
  {
    "key": "CO",
    "value": 26916
  },
  {
    "key": "UT",
    "value": 23212
  },
  {
    "key": "AZ",
    "value": 43411
  },
  {
    "key": "NM",
    "value": 3889
  },
  {
    "key": "NV",
    "value": 7389
  },
  {
    "key": "VT",
    "value": 418
  },
  {
    "key": "MS",
    "value": 4586
  },
  {
    "key": "AR",
    "value": 1019
  },
  {
    "key": "MT",
    "value": 434
  },
  {
    "key": "ME",
    "value": 1580
  },
  {
    "key": "ND",
    "value": 37
  },
  {
    "key": "WY",
    "value": 438
  },
  {
    "key": "ID",
    "value": 1352
  },
  {
    "key": "SD",
    "value": 44
  }
]